draglinecache/mongo.py
draglinecache/cache.py
draglinecache/__init__.py
draglinecache-0.1.dist-info/RECORD
draglinecache-0.1.dist-info/WHEEL
draglinecache-0.1.dist-info/METADATA
draglinecache-0.1.dist-info/DESCRIPTION.rst
draglinecache-0.1.dist-info/metadata.json
draglinecache-0.1.dist-info/top_level.txt
