Metadata-Version: 2.0
Name: draglinecache
Version: 0.1
Summary: Caching interface for dragline
Home-page: http://www.inzyte.com
Author: Ashwin Rajeev
Author-email: ashwin@inzyte.com
License: UNKNOWN
Platform: UNKNOWN
Requires-Dist: pymongo
